Workbook
Name aporte: Simulador!$D$18
Name aporte_inicial: Simulador!$D$21
Name investimento_mensal: Simulador!$C$33
Name patrimonio: Simulador!$D$22
Name qtd_anos: Simulador!$D$19
Name rendimento_carteira: Simulador!$D$14
Name salario: Simulador!$D$13
Name sugestao_investimento: Simulador!$D$15
Name taxa_mensal: Simulador!$D$20

Sheet Simulador
B12: CONFIGURAÇÕES
B13: Salário | D13: 4000
B14: Rendimento carteira | D14: 0.02
B15: Sugestão de investimento (30%) | D15: =salario*30% -> 1200
B17: INVESTIMENTO MENSAL
B18: Quanto investir por mês? | D18: 300
B19: Por quantos anos? | D19: 10
B20: Taxa de rendimento mensal? | D20: 0.01
B21: Qual o valor de aporte inicial? | D21: 2500
B22: Patrimônio acumulado? | D22: =FV(taxa_mensal,qtd_anos*12,aporte*-1,aporte_inicial*-1) -> 77262.574
B23: Dividendos mensais? | D23: =patrimonio*rendimento_carteira -> 1545.2515
A25: 2 | B25: Cenários | D25: Dividendo
A26: 5 | B26: Quanto em 2 anos? | C26: =FV($D$20,$A25*12,$D$18*-1,aporte_inicial*-1) -> 11266.376 | D26: =C26*rendimento_carteira -> 225.32752
A27: 10 | B27: Quanto em 5 anos? | C27: =FV($D$20,$A26*12,$D$18*-1,aporte_inicial*-1) -> 29042.643 | D27: =C27*rendimento_carteira -> 580.85285
A28: 20 | B28: Quanto em 10 anos? | C28: =FV($D$20,$A27*12,$D$18*-1,aporte_inicial*-1) -> 77262.574 | D28: =C28*rendimento_carteira -> 1545.2515
A29: 30 | B29: Quanto em 20 anos? | C29: =FV($D$20,$A28*12,$D$18*-1,aporte_inicial*-1) -> 324007.99 | D29: =C29*rendimento_carteira -> 6480.1599
B30: Quanto em 30 anos? | C30: =FV($D$20,$A29*12,$D$18*-1,aporte_inicial*-1) -> 1138363.3 | D30: =C30*rendimento_carteira -> 22767.267
B32: PERFIL | C32: Agressivo
B33: VALOR A SER INVESTIDO POR MÊS | C33: =aporte -> 300
B35: TIPO DE FII | C35: Percentual sugerido | D35: Valores
B36: PAPEL | C36: =VLOOKUP($C$32&"-"&B36,Apoio!$A:$D,4,) -> 0.5 | D36: =C36*investimento_mensal -> 150
B37: TIJOLO | C37: =VLOOKUP($C$32&"-"&B37,Apoio!$A:$D,4,) -> 0.1 | D37: =C37*investimento_mensal -> 30
B38: HÍBRIDOS | C38: =VLOOKUP($C$32&"-"&B38,Apoio!$A:$D,4,) -> 0.05 | D38: =C38*investimento_mensal -> 15
B39: FOFs | C39: =VLOOKUP($C$32&"-"&B39,Apoio!$A:$D,4,) -> 0.05 | D39: =C39*investimento_mensal -> 15
B40: DESENVOLVIMENTO | C40: =VLOOKUP($C$32&"-"&B40,Apoio!$A:$D,4,) -> 0.2 | D40: =C40*investimento_mensal -> 60
B41: HOTELARIAS | C41: =VLOOKUP($C$32&"-"&B41,Apoio!$A:$D,4,) -> 0.1 | D41: =C41*investimento_mensal -> 30
B42: TOTAL | D42: =SUM(D36:D41) -> 300

Sheet Apoio
A2: CHAVE | B2: PERFIL | C2: TIPO DE FII | D2: Percentual sugerido
A3: =B3&"-"&C3 -> Conservador-PAPEL | B3: Conservador | C3: PAPEL | D3: 0.3
A4: =B4&"-"&C4 -> Conservador-TIJOLO | B4: Conservador | C4: TIJOLO | D4: 0.5
A5: =B5&"-"&C5 -> Conservador-HÍBRIDOS | B5: Conservador | C5: HÍBRIDOS | D5: 0.1
A6: =B6&"-"&C6 -> Conservador-FOFs | B6: Conservador | C6: FOFs | D6: 0.1
A7: =B7&"-"&C7 -> Conservador-DESENVOLVIMENTO | B7: Conservador | C7: DESENVOLVIMENTO | D7: 0
A8: =B8&"-"&C8 -> Conservador-HOTELARIAS | B8: Conservador | C8: HOTELARIAS | D8: 0
A9: =B9&"-"&C9 -> Moderado-PAPEL | B9: Moderado | C9: PAPEL | D9: 0.32
A10: =B10&"-"&C10 -> Moderado-TIJOLO | B10: Moderado | C10: TIJOLO | D10: 0.35
A11: =B11&"-"&C11 -> Moderado-HÍBRIDOS | B11: Moderado | C11: HÍBRIDOS | D11: 0.08
A12: =B12&"-"&C12 -> Moderado-FOFs | B12: Moderado | C12: FOFs | D12: 0.05
A13: =B13&"-"&C13 -> Moderado-DESENVOLVIMENTO | B13: Moderado | C13: DESENVOLVIMENTO | D13: 0.1
A14: =B14&"-"&C14 -> Moderado-HOTELARIAS | B14: Moderado | C14: HOTELARIAS | D14: 0.1
... A20: =B20&"-"&C20 -> Agressivo-HOTELARIAS | B20: Agressivo | C20: HOTELARIAS | D20: 0.1
